p4pillon/__init__.py
p4pillon/composite_handler.py
p4pillon/definitions.py
p4pillon/nthandlers.py
p4pillon/pvrecipe.py
p4pillon/utils.py
p4pillon/asyncio/__init__.py
p4pillon/asyncio/pvrecipe.py
p4pillon/nt/__init__.py
p4pillon/nt/enum.py
p4pillon/rules/__init__.py
p4pillon/rules/alarm_ntenum_rule.py
p4pillon/rules/alarm_rule.py
p4pillon/rules/control_rule.py
p4pillon/rules/read_only_rule.py
p4pillon/rules/rules.py
p4pillon/rules/timestamp_rule.py
p4pillon/rules/value_alarm_rule.py
p4pillon/server/README.md
p4pillon/server/__init__.py
p4pillon/server/asyncio.py
p4pillon/server/cli.py
p4pillon/server/raw.py
p4pillon/server/simpleserver.py
p4pillon/server/thread.py
p4pillon/thread/__init__.py
p4pillon/thread/config_reader.py
p4pillon/thread/pvrecipe.py
p4pillon/thread/server.py
p4pillon/thread/sharednt.py
p4pillon-0.1.1.dist-info/METADATA
p4pillon-0.1.1.dist-info/WHEEL
p4pillon-0.1.1.dist-info/licenses/LICENSE
p4pillon-0.1.1.dist-info/RECORD
