Metadata-Version: 2.4
Name: p4pillon
Version: 0.1.1
Summary: Add your description here
Project-URL: Repository, https://github.com/epics-base/p4p
Author-email: Ivan Finch <ivan.finch@stfc.ac.uk>, Ajit Kurup <a.kurup@imperial.ac.uk>, Kathryn Baker <k.baker@stfc.ac.uk>, Aqeel AlShafei <aqeel.alshafei@stfc.ac.uk>
Maintainer-email: Ivan Finch <ivan.finch@stfc.ac.uk>
License: BSD-3-Clause
License-File: LICENSE
Keywords: epics,p4p,pva,pvaccess
Classifier: Development Status :: 2 - Pre-Alpha
Classifier: Environment :: Console
Classifier: Intended Audience :: Developers
Classifier: License :: OSI Approved :: BSD License
Classifier: Programming Language :: Python
Classifier: Typing :: Typed
Requires-Python: >=3.10
Requires-Dist: p4p>=4.2.1
Requires-Dist: pyyaml>=6.0.2
Provides-Extra: dist
Requires-Dist: build>=1.2.2.post1; extra == 'dist'
Requires-Dist: twine>=6.1.0; extra == 'dist'
Provides-Extra: test
Requires-Dist: coverage>7.9; extra == 'test'
Requires-Dist: pytest>=8.4; extra == 'test'
Requires-Dist: ruff>=0.12; extra == 'test'
